git_tools/__init__.py
git_tools/clone.py
git_tools/command_line.py
git_tools/process.py
git_tools/scan.py
git_tools/utils/__init__.py
git_tools/utils/misc.py
git_tools/utils/shell.py
git_tools/utils/types.py
git_tools-0.0.1.dist-info/LICENSE
git_tools-0.0.1.dist-info/METADATA
git_tools-0.0.1.dist-info/WHEEL
git_tools-0.0.1.dist-info/entry_points.txt
git_tools-0.0.1.dist-info/top_level.txt
git_tools-0.0.1.dist-info/RECORD
