Metadata-Version: 2.1
Name: git-tools
Version: 0.0.1
Summary: UNKNOWN
Home-page: https://github.com/rkhullar/git-tools
Author: Rajan Khullar
Author-email: rkhullar03@gmail.com
License: MIT
Keywords: git bitbucket
Platform: UNKNOWN
Requires-Python: ~=3.6
Requires-Dist: requests (~=2.22)
